ceco/__init__.py
ceco/benchmark.py
ceco/cec/__init__.py
ceco/cec/ackley.py
ceco/cec/bent_cigar.py
ceco/cec/different_power.py
ceco/cec/discus.py
ceco/cec/ellipsoid.py
ceco/cec/elliptic.py
ceco/cec/expanded_schaffer_f6.py
ceco/cec/griewank.py
ceco/cec/happycat.py
ceco/cec/hgbat.py
ceco/cec/katsuura.py
ceco/cec/levy.py
ceco/cec/rastrigin.py
ceco/cec/rosenbrock.py
ceco/cec/schwefel1_2.py
ceco/cec/schwefel2_13.py
ceco/cec/shubert.py
ceco/cec/sphere.py
ceco/cec/step_function.py
ceco/cec/vincent.py
ceco/cec/weierstrass.py
ceco/cec/zakharov.py
ceco/coco/__init__.py
ceco/coco/attractive_sector.py
ceco/coco/bent_cigar.py
ceco/coco/buche_rastrigin.py
ceco/coco/composite_griewank_rosenbrock_function_f8f2.py
ceco/coco/different_power.py
ceco/coco/discus.py
ceco/coco/ellipsoidal.py
ceco/coco/katsuura.py
ceco/coco/linear_slope.py
ceco/coco/rastrigin.py
ceco/coco/rosenbrock.py
ceco/coco/schaffer_f7.py
ceco/coco/schwefel.py
ceco/coco/sharp_ridge.py
ceco/coco/sphere.py
ceco/coco/step_ellipsoidal.py
ceco/coco/weierstrass.py
ceco/rw/__init__.py
ceco-1.0.10.dist-info/licenses/LICENSE
ceco-1.0.10.dist-info/METADATA
ceco-1.0.10.dist-info/WHEEL
ceco-1.0.10.dist-info/top_level.txt
ceco-1.0.10.dist-info/RECORD
